{
    "0304": {
        "RAM_INFO": [
            [
                320,
                23,
                8,
                22
            ],
            [
                320,
                254,
                16,
                1
            ],
            [
                320,
                0,
                7,
                23
            ]
        ],
        "DICT": [
            [
                1,
                0
            ],
            [
                1,
                12
            ]
        ],
        "ANIM_INFO": [
            [
                2,
                1,
                -14,
                -16,
                0,
                -128,
                -128,
                -128
            ],
            [
                0,
                1,
                -15,
                -14,
                0,
                -128,
                -128,
                -128
            ]
        ],
        "POS": [
            [
                1,
                0
            ],
            [
                1,
                10
            ]
        ],
        "ANIMATION": [
            [
                [
                    0,
                    0,
                    0,
                    -255,
                    0
                ]
            ],
            [
                [
                    1,
                    0,
                    0,
                    -255,
                    0
                ]
            ]
        ]
    }
}